setup.py
anoa/__init__.py
anoa/algorithms.py
anoa/basis.py
anoa/minimise.py
anoa/misc.py
anoa/regularisers.py
anoa/temp.py
anoa.egg-info/PKG-INFO
anoa.egg-info/SOURCES.txt
anoa.egg-info/dependency_links.txt
anoa.egg-info/not-zip-safe
anoa.egg-info/requires.txt
anoa.egg-info/top_level.txt
anoa/core/__init__.py
anoa/core/array.py
anoa/core/decorator.py
anoa/core/ops.py
anoa/functions/__init__.py
anoa/functions/array.py
anoa/functions/decorator.py
anoa/functions/fftpack.py
anoa/functions/logic.py
anoa/functions/math.py
anoa/operators/__init__.py
anoa/operators/fftpack.py
anoa/operators/logic.py
anoa/operators/math.py
anoa/test/__init__.py
anoa/test/all_test.py
anoa/test/array_test.py
anoa/test/basic_test.py
anoa/test/fftpack_test.py
anoa/test/math_test.py
anoa/test/test_compsense.py