Metadata-Version: 1.1
Name: anoa
Version: 0.1.1a0
Summary: A differentiable programming for scientists
Home-page: https://github.com/mfkasim91/anoa
Author: mfkasim91
Author-email: firman.kasim@gmail.com
License: MIT
Keywords: autodiff compressed-sensing differentiable-programming optimization
Platform: UNKNOWN
Classifier: Development Status :: 3 - Alpha
Classifier: Intended Audience :: Science/Research
Classifier: Topic :: Scientific/Engineering
Classifier: Topic :: Scientific/Engineering :: Physics
Classifier: Topic :: Scientific/Engineering :: Mathematics
Classifier: License :: OSI Approved :: MIT License
Classifier: Programming Language :: Python :: 2.7
